zhwanfirst/__init__.py
zhwanfirst/gifconverter.py
zhwanfirst-1.0.0.dist-info/LICENSE
zhwanfirst-1.0.0.dist-info/METADATA
zhwanfirst-1.0.0.dist-info/WHEEL
zhwanfirst-1.0.0.dist-info/top_level.txt
zhwanfirst-1.0.0.dist-info/RECORD
